HISTORY.rst
LICENSE
MANIFEST.in
README.rst
setup.py
Doga/__init__.py
Doga/doga.py
Doga/statistics.py
Doga/thread_jobs.py
Doga.egg-info/PKG-INFO
Doga.egg-info/SOURCES.txt
Doga.egg-info/dependency_links.txt
Doga.egg-info/entry_points.txt
Doga.egg-info/requires.txt
Doga.egg-info/top_level.txt
Doga/config/__init__.py
Doga/config/config.ini
Doga/config/configer.py
Doga/interfaces/__init__.py
Doga/interfaces/gui.py
Doga/interfaces/sockets.py
Doga/logs/__init__.py
Doga/logs/generator.py
Doga/parsers/__init__.py
Doga/parsers/packet.py
Doga/parsers/payload.py