Metadata-Version: 1.0
Name: Doga
Version: 0.2.0
Summary: HTTP log monitoring console for Humans
Home-page: https://github.com/pravj/Doga
Author: Pravendra Singh
Author-email: hackpravj@gmail.com
License: MIT
Keywords: http log monitor console doga
Platform: UNKNOWN
